xoto3/__about__.py
xoto3/__init__.py
xoto3/backoff.py
xoto3/cloudformation/__init__.py
xoto3/cloudwatch/__init__.py
xoto3/cloudwatch/insights.py
xoto3/cloudwatch/log_groups.py
xoto3/cloudwatch/logs/__init__.py
xoto3/cloudwatch/logs/events.py
xoto3/cloudwatch/logs/funnel.py
xoto3/cloudwatch/metrics.py
xoto3/cloudwatch/utils.py
xoto3/dynamodb/README.md
xoto3/dynamodb/__init__.py
xoto3/dynamodb/asynch.py
xoto3/dynamodb/batch_get.py
xoto3/dynamodb/batch_write.py
xoto3/dynamodb/conditions.py
xoto3/dynamodb/constants.py
xoto3/dynamodb/exceptions.py
xoto3/dynamodb/get.py
xoto3/dynamodb/paginate.py
xoto3/dynamodb/prewrite.py
xoto3/dynamodb/put.py
xoto3/dynamodb/query.py
xoto3/dynamodb/streams/__init__.py
xoto3/dynamodb/streams/consume.py
xoto3/dynamodb/streams/records.py
xoto3/dynamodb/streams/shards.py
xoto3/dynamodb/stringset.py
xoto3/dynamodb/types.py
xoto3/dynamodb/update/__init__.py
xoto3/dynamodb/update/builders.py
xoto3/dynamodb/update/core.py
xoto3/dynamodb/update/diff.py
xoto3/dynamodb/update/retry.py
xoto3/dynamodb/update/utils.py
xoto3/dynamodb/update/versioned.py
xoto3/dynamodb/utils/__init__.py
xoto3/dynamodb/utils/expressions.py
xoto3/dynamodb/utils/index.py
xoto3/dynamodb/utils/serde.py
xoto3/dynamodb/utils/table.py
xoto3/dynamodb/utils/truth.py
xoto3/dynamodb/write_versioned/README.md
xoto3/dynamodb/write_versioned/__init__.py
xoto3/dynamodb/write_versioned/api2.py
xoto3/dynamodb/write_versioned/ddb_api.py
xoto3/dynamodb/write_versioned/errors.py
xoto3/dynamodb/write_versioned/keys.py
xoto3/dynamodb/write_versioned/lazy_batch_gets.py
xoto3/dynamodb/write_versioned/modify.py
xoto3/dynamodb/write_versioned/prepare.py
xoto3/dynamodb/write_versioned/read.py
xoto3/dynamodb/write_versioned/retry.py
xoto3/dynamodb/write_versioned/run.py
xoto3/dynamodb/write_versioned/specify.py
xoto3/dynamodb/write_versioned/types.py
xoto3/errors.py
xoto3/lam/__init__.py
xoto3/lam/event_records.py
xoto3/lam/finalize.py
xoto3/lam/maintenance.py
xoto3/lam/types.py
xoto3-2.0.1.dist-info/LICENSE
xoto3-2.0.1.dist-info/METADATA
xoto3-2.0.1.dist-info/WHEEL
xoto3-2.0.1.dist-info/RECORD
