Metadata-Version: 2.3
Name: xoto3
Version: 2.0.1
Summary: High level utilities for a subset of boto3 operations common for AWS serverless development in Python.
Author: Peter Gaultney
Author-email: pgaultney@xoi.io
Requires-Python: >=3.9,<4.0
Classifier: Programming Language :: Python :: 3
Classifier: Programming Language :: Python :: 3.9
Classifier: Programming Language :: Python :: 3.10
Classifier: Programming Language :: Python :: 3.11
Classifier: Programming Language :: Python :: 3.12
Classifier: Programming Language :: Python :: 3.13
Requires-Dist: boto3 (>=1.9)
Requires-Dist: typing-extensions
